ascii_art_library/__init__.py
ascii_art_library/ascii_art_library.py
ascii_art_library-0.0.6.dist-info/LICENSE
ascii_art_library-0.0.6.dist-info/METADATA
ascii_art_library-0.0.6.dist-info/WHEEL
ascii_art_library-0.0.6.dist-info/top_level.txt
ascii_art_library-0.0.6.dist-info/RECORD
