Metadata-Version: 2.1
Name: ascii-art-library
Version: 0.0.6
Summary: A library for converting an image to ascii art (simple text and html).
Author-email: AlDim <aldim.gr@gmail.com>
License: MIT License
Project-URL: Homepage, https://github.com/Al-Dim/ascii_art_library
Keywords: python,ascii,art,ascii art,generator,converter,image
Classifier: Programming Language :: Python :: 3
Classifier: License :: OSI Approved :: MIT License
Classifier: Operating System :: OS Independent
Requires-Python: >=3.6
License-File: LICENSE
Requires-Dist: pillow
